anyio_mqtt/__init__.py
anyio_mqtt/py.typed
anyio_mqtt/retry.py
anyio_mqtt/test_client.py
anyio_mqtt-0.3.2.dist-info/LICENSE
anyio_mqtt-0.3.2.dist-info/WHEEL
anyio_mqtt-0.3.2.dist-info/METADATA
anyio_mqtt-0.3.2.dist-info/RECORD
