Metadata-Version: 2.1
Name: anyio-mqtt
Version: 0.3.2
Summary: Very early work in progress of an AnyIO MQTT client
License: MIT
Author: Ellis Percival
Author-email: anyio-mqtt@failcode.co.uk
Requires-Python: >=3.6.2,<4.0.0
Classifier: License :: OSI Approved :: MIT License
Classifier: Programming Language :: Python :: 3
Classifier: Programming Language :: Python :: 3.10
Classifier: Programming Language :: Python :: 3.7
Classifier: Programming Language :: Python :: 3.8
Classifier: Programming Language :: Python :: 3.9
Requires-Dist: anyio (>=3.1.0,<4.0.0)
Requires-Dist: dataclasses (>=0.8,<0.9); python_version >= "3.6" and python_version < "3.7"
Requires-Dist: paho-mqtt (>=1.5.1,<2.0.0)
Requires-Dist: tenacity (>=7.0.0,<8.0.0)
